statictastic/__init__.py
statictastic/backends.py
statictastic/metadata.py
statictastic/progress.py
statictastic/management/__init__.py
statictastic/management/commands/__init__.py
statictastic/management/commands/create_iam_access_keys.py
statictastic/management/commands/syncmedia.py
statictastic/templatetags/__init__.py
statictastic/templatetags/statictastic.py
django_statictastic-4.0.0.dist-info/LICENSE
django_statictastic-4.0.0.dist-info/METADATA
django_statictastic-4.0.0.dist-info/NOTICE
django_statictastic-4.0.0.dist-info/WHEEL
django_statictastic-4.0.0.dist-info/top_level.txt
django_statictastic-4.0.0.dist-info/RECORD
